dev_health_ops/__init__.py
dev_health_ops/cli.py
dev_health_ops/investment_taxonomy.py
dev_health_ops/storage.py
dev_health_ops/utils.py
dev_health_ops/alembic/README
dev_health_ops/alembic/__init__.py
dev_health_ops/alembic/env.py
dev_health_ops/alembic/script.py.mako
dev_health_ops/alembic/versions/1a2b3c4d5e6f_add_atlassian_ops_tables.py
dev_health_ops/alembic/versions/9f2f70b48ab5_initial_migration.py
dev_health_ops/alembic/versions/__init__.py
dev_health_ops/alembic/versions/c3a7b2d4e5f6_add_cicd_deploy_incident_tables.py
dev_health_ops/alembic/versions/d4b8e3f5a1c2_rename_mergestat_synced_at.py
dev_health_ops/alembic/versions/e1f2a3b4c5d6_add_pr_body.py
dev_health_ops/alembic/versions/f2b3c4d5e6f7_add_jira_project_ops_team_links.py
dev_health_ops/analytics/__init__.py
dev_health_ops/analytics/complexity.py
dev_health_ops/analytics/investment.py
dev_health_ops/analytics/issue_types.py
dev_health_ops/analytics/metrics.py
dev_health_ops/analytics/work_units.py
dev_health_ops/analytics/jobs/__init__.py
dev_health_ops/api/__init__.py
dev_health_ops/api/main.py
dev_health_ops/api/runner.py
dev_health_ops/api/graphql/__init__.py
dev_health_ops/api/graphql/app.py
dev_health_ops/api/graphql/authz.py
dev_health_ops/api/graphql/cache_invalidation.py
dev_health_ops/api/graphql/caching.py
dev_health_ops/api/graphql/context.py
dev_health_ops/api/graphql/cost.py
dev_health_ops/api/graphql/errors.py
dev_health_ops/api/graphql/pagination.py
dev_health_ops/api/graphql/persisted.py
dev_health_ops/api/graphql/persisted_queries.json
dev_health_ops/api/graphql/pubsub.py
dev_health_ops/api/graphql/schema.py
dev_health_ops/api/graphql/subscriptions.py
dev_health_ops/api/graphql/loaders/__init__.py
dev_health_ops/api/graphql/loaders/analytics_loader.py
dev_health_ops/api/graphql/loaders/base.py
dev_health_ops/api/graphql/loaders/dimension_loader.py
dev_health_ops/api/graphql/loaders/repo_loader.py
dev_health_ops/api/graphql/loaders/team_loader.py
dev_health_ops-0.4.0.dist-info/licenses/LICENSE.md
dev_health_ops-0.4.0.dist-info/METADATA
dev_health_ops-0.4.0.dist-info/WHEEL
dev_health_ops-0.4.0.dist-info/entry_points.txt
dev_health_ops-0.4.0.dist-info/top_level.txt
dev_health_ops-0.4.0.dist-info/RECORD
