Metadata-Version: 2.4
Name: dev-health-ops
Version: 0.4.0
Summary: Open Source Development Team Operation Analytics
Author-email: Chris Geo <chris@example.com>
License: MIT
Project-URL: Repository, https://github.com/chrisgeo/dev-health-ops
Project-URL: Issues, https://github.com/chrisgeo/dev-health-ops/issues
Keywords: metrics,git,analytics,developer-experience,grafana
Classifier: Development Status :: 4 - Beta
Classifier: Intended Audience :: Developers
Classifier: Programming Language :: Python :: 3
Classifier: Programming Language :: Python :: 3.10
Classifier: Programming Language :: Python :: 3.11
Classifier: Programming Language :: Python :: 3.12
Classifier: License :: OSI Approved :: MIT License
Classifier: Operating System :: OS Independent
Requires-Python: >=3.10
License-File: LICENSE.md
Requires-Dist: tqdm
Requires-Dist: sqlalchemy
Requires-Dist: clickhouse-connect
Requires-Dist: fastapi
Requires-Dist: httpx
Requires-Dist: psycopg2-binary
Requires-Dist: asyncpg
Requires-Dist: aiosqlite
Requires-Dist: python-gitlab
Requires-Dist: GitPython
Requires-Dist: PyGithub<3.0.0,>=2.1.0
Requires-Dist: requests
Requires-Dist: pydantic
Requires-Dist: PyYAML
Requires-Dist: typing_extensions
Requires-Dist: jira
Requires-Dist: alembic
Requires-Dist: motor
Requires-Dist: uvicorn
Requires-Dist: radon
Requires-Dist: openai
Requires-Dist: anthropic
Requires-Dist: strawberry-graphql[fastapi]
Requires-Dist: celery[redis]>=5.3.0
Requires-Dist: redis>=5.0.0
Requires-Dist: atlassian-gen-client>=0.1.0b3
Requires-Dist: pytest-xdist<4.0.0,>=3.8.0
Provides-Extra: dev
Requires-Dist: mypy; extra == "dev"
Requires-Dist: black; extra == "dev"
Requires-Dist: flake8; extra == "dev"
Requires-Dist: isort; extra == "dev"
Requires-Dist: pytest; extra == "dev"
Requires-Dist: pytest-asyncio; extra == "dev"
Requires-Dist: pytest-cov; extra == "dev"
Dynamic: license-file
